matrix_quant/__init__.py
matrix_quant/matrix.py
equant-0.0.2.dist-info/LICENSE.txt
equant-0.0.2.dist-info/METADATA
equant-0.0.2.dist-info/WHEEL
equant-0.0.2.dist-info/top_level.txt
equant-0.0.2.dist-info/RECORD
